setup.py
processimg/__init__.py
processimg/filters.py
processimg.egg-info/PKG-INFO
processimg.egg-info/SOURCES.txt
processimg.egg-info/dependency_links.txt
processimg.egg-info/requires.txt
processimg.egg-info/top_level.txt