Metadata-Version: 2.1
Name: processimg
Version: 0.1
Summary: A package for image processing
Author: Kaique Zeza
Author-email: kaiquezeza@email.com
